pycornmarsh/__init__.py
pycornmarsh/generator.py
pycornmarsh/marshmallow.py
pycornmarsh/predicates.py
pycornmarsh-0.0.1rc2.dist-info/METADATA
pycornmarsh-0.0.1rc2.dist-info/WHEEL
pycornmarsh-0.0.1rc2.dist-info/top_level.txt
pycornmarsh-0.0.1rc2.dist-info/RECORD
